cjdg_api.py
cjdg_api-1.0.0.dist-info/LICENSE
cjdg_api-1.0.0.dist-info/WHEEL
cjdg_api-1.0.0.dist-info/METADATA
cjdg_api-1.0.0.dist-info/RECORD
