Metadata-Version: 2.1
Name: cjdg_api
Version: 1.0.0
Summary: 超导移动端API大全
Home-page: http://www.chaojidaogou.com
License: UNKNOWN
Author: Rqk
Author-email: renqiukai@qq.com
Classifier: License :: OSI Approved :: MIT License
